tbscm/__init__.py
tbscm/synthetic_controls.py
tbscm/base/__init__.py
tbscm/base/base_synthetic_controls.py
tbscm/estimator/__init__.py
tbscm/estimator/constrained_ols.py
tbscm/utils/__init__.py
tbscm/utils/bootstrap.py
tbscm/utils/data.py
tbscm/utils/exceptions.py
tbscm/utils/sanity_check.py
tbscm/utils/tools.py
tbscm-0.0.6.dist-info/LICENSE
tbscm-0.0.6.dist-info/METADATA
tbscm-0.0.6.dist-info/WHEEL
tbscm-0.0.6.dist-info/top_level.txt
tbscm-0.0.6.dist-info/RECORD
